[
  {
    "Graph": "Graph #1",
    "Area": "APC"
  },
  {
    "Graph": "Graph #2",
    "Area": "Entrance Guards"
  },
  {
    "Graph": "Graph #3",
    "Area": "Warehouse"
  },
  {
    "Graph": "Graph #6",
    "Area": "Barracks to Power Building"
  },
  {
    "Graph": "Graph #7",
    "Area": "Helipad"
  },
  {
    "Graph": "Graph #8",
    "Area": "Last Base"
  },
  {
    "Graph": "Graph #9",
    "Area": "Watchtower Last Base"
  },
  {
    "Graph": "Graph #11",
    "Area": "Limo"
  },
  {
    "Graph": "Graph #12",
    "Area": "Priboi's Warehouse"
  },
  {
    "Graph": "Graph #13",
    "Area": "Near Limo 2nd Base"
  },
  {
    "Graph": "Graph #14",
    "Area": "Near Limo 2nd Base"
  },
  {
    "Graph": "Graph #15",
    "Area": "Near Limo 2nd Base Upstairs"
  },
  {
    "Graph": "Graph #16",
    "Area": "Near Limo 2nd Base"
  },
  {
    "Graph": "Graph #17",
    "Area": "Area Between Heli and 2nd Base"
  },
  {
    "Graph": "Graph #18",
    "Area": "Area Between Heli and 2nd Base"
  },
  {
    "Graph": "Graph #19",
    "Area": "Area Between Heli and 2nd Base"
  },
  {
    "Graph": "Graph #20",
    "Area": "Area Between Heli and 2nd Base"
  },
  {
    "Graph": "Graph #21",
    "Area": "Area Between Heli and 2nd Base"
  },
  {
    "Graph": "Graph #23",
    "Area": "Uzi Soldier Tower"
  },
  {
    "Graph": "Graph #24",
    "Area": "Cutscene Area"
  },
  {
    "Graph": "Graph #25",
    "Area": "Cutscene Area"
  },
  {
    "Graph": "Graph #26",
    "Area": "Area Between Heli and 2nd Base"
  }
]